aiopywttr/__init__.py
aiopywttr/_wttr.py
aiopywttr/py.typed
aiopywttr-3.0.2.dist-info/METADATA
aiopywttr-3.0.2.dist-info/WHEEL
aiopywttr-3.0.2.dist-info/licenses/LICENSE
aiopywttr-3.0.2.dist-info/RECORD
