Metadata-Version: 2.4
Name: aiopywttr
Version: 3.0.2
Summary: Asynchronous wrapper for wttr.in weather API
Project-URL: documentation, https://aiopywttr.readthedocs.io
Project-URL: repository, https://github.com/monosans/aiopywttr
Author-email: monosans <hsyqixco@protonmail.com>
License-Expression: MIT
License-File: LICENSE
Keywords: forecast
Classifier: Framework :: AsyncIO
Classifier: Framework :: Pydantic
Classifier: Framework :: Pydantic :: 2
Classifier: Framework :: aiohttp
Classifier: Natural Language :: English
Classifier: Operating System :: OS Independent
Classifier: Programming Language :: Python
Classifier: Programming Language :: Python :: 3 :: Only
Classifier: Programming Language :: Python :: 3.9
Classifier: Programming Language :: Python :: 3.10
Classifier: Programming Language :: Python :: 3.11
Classifier: Programming Language :: Python :: 3.12
Classifier: Programming Language :: Python :: 3.13
Classifier: Programming Language :: Python :: 3.14
Classifier: Programming Language :: Python :: 3.15
Classifier: Typing :: Typed
Requires-Python: >=3.9
Requires-Dist: aiohttp>=3.7
Requires-Dist: pywttr-models<3,>=2
Requires-Dist: typing-extensions>=4
